threadfix_api/threadfix.py
threadfix_api/__init__.py
threadfix_api-1.1.1.dist-info/DESCRIPTION.rst
threadfix_api-1.1.1.dist-info/METADATA
threadfix_api-1.1.1.dist-info/metadata.json
threadfix_api-1.1.1.dist-info/RECORD
threadfix_api-1.1.1.dist-info/top_level.txt
threadfix_api-1.1.1.dist-info/WHEEL
