Metadata-Version: 2.0
Name: threadfix-api
Version: 1.1.1
Summary: An API wrapper to facilitate interactions with ThreadFix.
Home-page: https://github.com/aparsons/threadfix_api
Author: Adam Parsons
Author-email: adam@aparsons.net
License: MIT
Download-URL: https://github.com/aparsons/threadfix_api/tarball/1.1.1
Keywords: threadfix,api,security,software
Platform: UNKNOWN
Classifier: Development Status :: 4 - Beta
Classifier: Intended Audience :: Developers
Classifier: Natural Language :: English
Classifier: License :: OSI Approved :: MIT License
Classifier: Topic :: Software Development
Classifier: Topic :: Software Development :: Libraries :: Python Modules
Classifier: Programming Language :: Python :: 3
Classifier: Programming Language :: Python :: 3.2
Classifier: Programming Language :: Python :: 3.3
Classifier: Programming Language :: Python :: 3.4
Requires-Dist: requests
